subgrounds/__init__.py
subgrounds/client/__init__.py
subgrounds/client/async_.py
subgrounds/client/base.py
subgrounds/client/sync.py
subgrounds/contrib/README.md
subgrounds/contrib/dash/__init__.py
subgrounds/contrib/dash/abcs.py
subgrounds/contrib/dash/components.py
subgrounds/contrib/plotly/__init__.py
subgrounds/contrib/plotly/figure.py
subgrounds/contrib/plotly/traces.py
subgrounds/dash_wrappers.py
subgrounds/dataframe_utils.py
subgrounds/errors.py
subgrounds/pagination/__init__.py
subgrounds/pagination/pagination.py
subgrounds/pagination/preprocess.py
subgrounds/pagination/strategies.py
subgrounds/pagination/utils.py
subgrounds/plotly_wrappers.py
subgrounds/query.py
subgrounds/resources/introspection.graphql
subgrounds/schema.py
subgrounds/subgraph/__init__.py
subgrounds/subgraph/fieldpath.py
subgrounds/subgraph/filter.py
subgrounds/subgraph/object.py
subgrounds/subgraph/subgraph.py
subgrounds/subgrounds.py
subgrounds/transform/__init__.py
subgrounds/transform/apply.py
subgrounds/transform/base.py
subgrounds/transform/defaults.py
subgrounds/transform/transforms.py
subgrounds/transform/utils.py
subgrounds/utils.py
subgrounds-1.9.1.dist-info/LICENSE
subgrounds-1.9.1.dist-info/WHEEL
subgrounds-1.9.1.dist-info/METADATA
subgrounds-1.9.1.dist-info/RECORD
