Metadata-Version: 2.1
Name: subgrounds
Version: 1.9.1
Summary: A Pythonic data access layer for applications querying data from The Graph Network.
Home-page: https://github.com/0xPlaygrounds/subgrounds
Keywords: graph,subgrounds,graphql,subgraph
Author: cvauclair
Author-email: cvauclair@playgrounds.network
Requires-Python: >=3.10,<4.0
Classifier: Programming Language :: Python :: 3
Classifier: Programming Language :: Python :: 3.10
Classifier: Programming Language :: Python :: 3.11
Provides-Extra: all
Provides-Extra: dash
Provides-Extra: plotly
Requires-Dist: dash (>=2.3.1,<3.0.0) ; extra == "dash" or extra == "all"
Requires-Dist: httpx[http2] (>=0.25.1,<0.26.0)
Requires-Dist: pandas (>=2.1,<3.0)
Requires-Dist: pipe (>=2.0,<3.0)
Requires-Dist: plotly (>=5.14.1,<6.0.0) ; extra == "plotly" or extra == "all"
Requires-Dist: pydantic (>=2.0,<3.0)
Requires-Dist: pytest-asyncio
Project-URL: Repository, https://github.com/0xPlaygrounds/subgrounds
